INTERFACE_I2C_BUS.srcs/sources_1/imports/interface i2c/mock_i2c_slave.v
`timescale 1ns / 1ps

module mock_i2c_slave #(
    parameter SLAVE_ADDR = 7'h3C,
    parameter READ_DATA  = 8'hBB // Data to send when read by master
)(
    inout wire sda,
    input wire scl
);

    reg [7:0] shift_reg = 0;
    reg [3:0] bit_count = 0;
    reg sda_out = 0;
    reg sda_dir = 0; // 1 = output, 0 = input
    reg is_addressed = 0;
    reg is_read = 0;
    
    assign sda = (sda_dir == 1'b1) ? sda_out : 1'bz;

    // Event counters to detect START and STOP without multi-driver conflicts
    reg [7:0] start_count = 0;
    reg [7:0] stop_count = 0;
    reg [7:0] last_start_count = 0;
    reg [7:0] last_stop_count = 0;
    
    always @(negedge sda) begin
        if (scl == 1'b1) start_count <= start_count + 1; // START
    end
    
    always @(posedge sda) begin
        if (scl == 1'b1) stop_count <= stop_count + 1; // STOP
    end
    
    // State machine based on SCL
    always @(negedge scl) begin
        if (start_count != last_start_count) begin
            last_start_count <= start_count;
            bit_count <= 0;
            sda_dir <= 0;
            is_addressed <= 0;
        end else if (stop_count != last_stop_count) begin
            last_stop_count <= stop_count;
            sda_dir <= 0;
            is_addressed <= 0;
        end else begin
            if (!is_addressed) begin
                if (bit_count < 7) begin
                    shift_reg[6 - bit_count] <= sda;
                    bit_count <= bit_count + 1;
                end else if (bit_count == 7) begin
                    is_read <= sda;
                    if (shift_reg[6:0] == SLAVE_ADDR) begin
                        sda_dir <= 1;
                        sda_out <= 0; // ACK
                    end
                    bit_count <= bit_count + 1;
                end else if (bit_count == 8) begin
                    if (shift_reg[6:0] == SLAVE_ADDR) begin
                        is_addressed <= 1;
                        if (is_read) begin
                            shift_reg <= READ_DATA;
                            sda_dir <= 1;
                            sda_out <= READ_DATA[7];
                            bit_count <= 1;
                        end else begin
                            sda_dir <= 0;
                            bit_count <= 0;
                        end
                    end else begin
                        sda_dir <= 0;
                        bit_count <= 0;
                    end
                end
            end else begin
                // Data phase
                if (is_read) begin
                    // Read phase (slave transmits)
                    if (bit_count < 8) begin
                        sda_dir <= 1;
                        sda_out <= shift_reg[7 - bit_count];
                        bit_count <= bit_count + 1;
                    end else if (bit_count == 8) begin
                        sda_dir <= 0; // Release for Master ACK
                        bit_count <= 0;
                        is_addressed <= 0; // End after 1 byte for simplicity
                    end
                end else begin
                    // Write phase (slave receives)
                    if (bit_count < 7) begin
                        sda_dir <= 0;
                        shift_reg[7 - bit_count] <= sda;
                        bit_count <= bit_count + 1;
                    end else if (bit_count == 7) begin
                        sda_dir <= 1;
                        sda_out <= 0; // ACK
                        shift_reg[0] <= sda;
                        bit_count <= bit_count + 1;
                    end else if (bit_count == 8) begin
                        sda_dir <= 0;
                        bit_count <= 0;
                        is_addressed <= 0; // End after 1 byte
                    end
                end
            end
        end
    end

endmodule

interface i2c/i2c_master.v
`timescale 1ns / 1ps

module i2c_master #(
    parameter INPUT_CLK_FREQ = 50_000_000, // 50 MHz default
    parameter I2C_FREQ       = 100_000     // 100 kHz I2C clock
)(
    input  wire       clk,
    input  wire       rst_n,
    
    // Control interface
    input  wire       enable,      // Pulse high to start transaction
    input  wire       rw,          // 0 = write, 1 = read
    input  wire [6:0] addr,        // 7-bit target address
    input  wire [7:0] data_in,     // Data to write
    output reg  [7:0] data_out,    // Data read
    output reg        busy,        // High while transaction is ongoing
    output reg        ack_error,   // High if slave NACKs
    
    // I2C bus signals
    inout  wire       sda,
    output wire       scl
);

    // Derived parameters
    localparam DIVIDER = (INPUT_CLK_FREQ / I2C_FREQ) / 4; 
    // We divide by 4 because an I2C clock cycle has 4 phases: SCL low, SCL low-to-high, SCL high, SCL high-to-low

    // State Machine
    localparam IDLE    = 4'd0;
    localparam START   = 4'd1;
    localparam ADDR    = 4'd2;
    localparam ACK1    = 4'd3;
    localparam WRITE   = 4'd4;
    localparam READ    = 4'd5;
    localparam ACK2    = 4'd6;
    localparam STOP    = 4'd7;

    reg [3:0] state, next_state;
    reg [15:0] clk_count;
    reg [1:0]  i2c_phase;  // 00: SCL=0, 01: SCL=1 edge, 10: SCL=1, 11: SCL=0 edge
    reg i2c_clk_en;

    reg [7:0] tx_data;
    reg [7:0] rx_data;
    reg [2:0] bit_count;

    reg sda_out, sda_dir, scl_out;
    
    // Tri-state buffer for SDA
    assign sda = (sda_dir == 1'b1) ? sda_out : 1'bz;
    assign scl = scl_out;

    // Clock divider
    always @(posedge clk or negedge rst_n) begin
        if (!rst_n) begin
            clk_count <= 0;
            i2c_phase <= 0;
            i2c_clk_en <= 0;
        end else begin
            if (clk_count == DIVIDER - 1) begin
                clk_count <= 0;
                i2c_phase <= i2c_phase + 1;
                i2c_clk_en <= 1'b1;
            end else begin
                clk_count <= clk_count + 1;
                i2c_clk_en <= 1'b0;
            end
        end
    end

    // FSM sequential logic
    always @(posedge clk or negedge rst_n) begin
        if (!rst_n) begin
            state <= IDLE;
            busy <= 0;
            ack_error <= 0;
            bit_count <= 0;
            tx_data <= 0;
            rx_data <= 0;
            data_out <= 0;
            sda_out <= 1;
            sda_dir <= 1;
            scl_out <= 1;
        end else begin
            if (i2c_clk_en) begin
                case (state)
                    IDLE: begin
                        sda_out <= 1;
                        sda_dir <= 1;
                        scl_out <= 1;
                        busy <= 0;
                        if (enable) begin
                            state <= START;
                            tx_data <= {addr, rw};
                            busy <= 1;
                            ack_error <= 0;
                        end
                    end

                    START: begin
                        busy <= 1;
                        case (i2c_phase)
                            2'b00: begin sda_out <= 1; sda_dir <= 1; scl_out <= 1; end
                            2'b01: begin sda_out <= 1; scl_out <= 1; end
                            2'b10: begin sda_out <= 0; scl_out <= 1; end
                            2'b11: begin sda_out <= 0; scl_out <= 0; end
                        endcase
                        if (i2c_phase == 2'b11) begin
                            state <= ADDR;
                            bit_count <= 7;
                        end
                    end

                    ADDR: begin
                        case (i2c_phase)
                            2'b00: begin sda_dir <= 1; sda_out <= tx_data[bit_count]; scl_out <= 0; end
                            2'b01: scl_out <= 1;
                            2'b10: scl_out <= 1;
                            2'b11: scl_out <= 0;
                        endcase
                        if (i2c_phase == 2'b11) begin
                            if (bit_count == 0) state <= ACK1;
                            else bit_count <= bit_count - 1;
                        end
                    end

                    ACK1: begin
                        case (i2c_phase)
                            2'b00: begin sda_dir <= 0; scl_out <= 0; end // Release SDA for slave ACK
                            2'b01: scl_out <= 1;
                            2'b10: begin scl_out <= 1; ack_error <= sda; end // Sample ACK
                            2'b11: scl_out <= 0;
                        endcase
                        if (i2c_phase == 2'b11) begin
                            if (ack_error) begin
                                state <= STOP; // Stop on NACK
                            end else begin
                                bit_count <= 7;
                                if (rw == 0) begin // Write
                                    tx_data <= data_in;
                                    state <= WRITE;
                                end else begin // Read
                                    state <= READ;
                                end
                            end
                        end
                    end

                    WRITE: begin
                        case (i2c_phase)
                            2'b00: begin sda_dir <= 1; sda_out <= tx_data[bit_count]; scl_out <= 0; end
                            2'b01: scl_out <= 1;
                            2'b10: scl_out <= 1;
                            2'b11: scl_out <= 0;
                        endcase
                        if (i2c_phase == 2'b11) begin
                            if (bit_count == 0) state <= ACK2;
                            else bit_count <= bit_count - 1;
                        end
                    end

                    READ: begin
                        case (i2c_phase)
                            2'b00: begin sda_dir <= 0; scl_out <= 0; end // Release SDA to read
                            2'b01: scl_out <= 1;
                            2'b10: begin scl_out <= 1; rx_data[bit_count] <= sda; end // Sample Data
                            2'b11: scl_out <= 0;
                        endcase
                        if (i2c_phase == 2'b11) begin
                            if (bit_count == 0) begin
                                data_out <= rx_data;
                                state <= ACK2;
                            end else begin
                                bit_count <= bit_count - 1;
                            end
                        end
                    end

                    ACK2: begin
                        case (i2c_phase)
                            2'b00: begin 
                                if (rw == 0) begin
                                    sda_dir <= 0; // Wait for slave ACK if we wrote
                                end else begin
                                    sda_dir <= 1; sda_out <= 1; // Master NACK after read (for 1 byte read)
                                end
                                scl_out <= 0; 
                            end
                            2'b01: scl_out <= 1;
                            2'b10: begin 
                                scl_out <= 1; 
                                if (rw == 0) ack_error <= sda; // Check ACK from slave
                            end 
                            2'b11: scl_out <= 0;
                        endcase
                        if (i2c_phase == 2'b11) begin
                            state <= STOP;
                        end
                    end

                    STOP: begin
                        case (i2c_phase)
                            2'b00: begin sda_dir <= 1; sda_out <= 0; scl_out <= 0; end
                            2'b01: begin scl_out <= 1; end
                            2'b10: begin sda_out <= 1; scl_out <= 1; end // SDA low to high while SCL is high -> STOP
                            2'b11: begin sda_out <= 1; scl_out <= 1; end
                        endcase
                        if (i2c_phase == 2'b11) begin
                            state <= IDLE;
                            busy <= 0;
                        end
                    end

                    default: state <= IDLE;
                endcase
            end
        end
    end

endmodule

INTERFACE_I2C_BUS.srcs/sources_1/imports/interface i2c/top_controller.v
`timescale 1ns / 1ps

module top_controller (
    input  wire       clk,
    input  wire       rst_n,
    input  wire       start_demo,
    
    // Outputs to observe states
    output wire [7:0] eeprom_data,
    output wire       demo_done,
    output wire       error_flag,
    
    // I2C bus
    inout  wire       sda,
    output wire       scl
);

    // I2C Master Interface
    reg        i2c_enable;
    reg        i2c_rw;
    reg  [6:0] i2c_addr;
    reg  [7:0] i2c_data_in;
    wire [7:0] i2c_data_out;
    wire       i2c_busy;
    wire       i2c_ack_error;
    
    i2c_master #(
        .INPUT_CLK_FREQ(50_000_000),
        .I2C_FREQ(100_000)
    ) master_inst (
        .clk(clk),
        .rst_n(rst_n),
        .enable(i2c_enable),
        .rw(i2c_rw),
        .addr(i2c_addr),
        .data_in(i2c_data_in),
        .data_out(i2c_data_out),
        .busy(i2c_busy),
        .ack_error(i2c_ack_error),
        .sda(sda),
        .scl(scl)
    );

    // FSM States
    localparam S_IDLE            = 0;
    localparam S_WRITE_OLED      = 1;
    localparam S_WAIT_OLED       = 2;
    localparam S_DELAY           = 3; // Delay between transactions
    localparam S_WRITE_EEPROM_ADDR = 4;
    localparam S_WAIT_EEPROM_ADDR = 5;
    localparam S_READ_EEPROM     = 6;
    localparam S_WAIT_EEPROM     = 7;
    localparam S_DONE            = 8;
    localparam S_ERROR           = 9;

    reg [3:0] state;
    reg [7:0] captured_data;
    reg [15:0] delay_cnt;
    
    assign eeprom_data = captured_data;
    assign demo_done = (state == S_DONE);
    assign error_flag = (state == S_ERROR);

    always @(posedge clk or negedge rst_n) begin
        if (!rst_n) begin
            state <= S_IDLE;
            i2c_enable <= 0;
            i2c_rw <= 0;
            i2c_addr <= 0;
            i2c_data_in <= 0;
            captured_data <= 0;
            delay_cnt <= 0;
        end else begin
            case (state)
                S_IDLE: begin
                    i2c_enable <= 0;
                    if (start_demo && !i2c_busy) begin
                        // Start by writing to OLED (0x3C)
                        state <= S_WRITE_OLED;
                        i2c_addr <= 7'h3C;
                        i2c_rw <= 0;
                        i2c_data_in <= 8'hA5; // dummy data
                        i2c_enable <= 1;
                    end
                end

                S_WRITE_OLED: begin
                    if (i2c_busy) begin
                        i2c_enable <= 0;
                        state <= S_WAIT_OLED;
                    end
                end

                S_WAIT_OLED: begin
                    if (!i2c_busy) begin
                        if (i2c_ack_error) state <= S_ERROR;
                        else begin
                            state <= S_DELAY;
                            delay_cnt <= 0;
                        end
                    end
                end

                S_DELAY: begin
                    if (delay_cnt == 16'hFFFF) begin
                        state <= S_WRITE_EEPROM_ADDR;
                        i2c_addr <= 7'h50; // EEPROM address
                        i2c_rw <= 0;
                        i2c_data_in <= 8'h00; // Memory address 0x00
                        i2c_enable <= 1;
                    end else begin
                        delay_cnt <= delay_cnt + 1;
                    end
                end

                S_WRITE_EEPROM_ADDR: begin
                    if (i2c_busy) begin
                        i2c_enable <= 0;
                        state <= S_WAIT_EEPROM_ADDR;
                    end
                end

                S_WAIT_EEPROM_ADDR: begin
                    if (!i2c_busy) begin
                        if (i2c_ack_error) state <= S_ERROR;
                        else begin
                            state <= S_READ_EEPROM;
                            i2c_addr <= 7'h50;
                            i2c_rw <= 1; // READ mode
                            i2c_enable <= 1;
                        end
                    end
                end

                S_READ_EEPROM: begin
                    if (i2c_busy) begin
                        i2c_enable <= 0;
                        state <= S_WAIT_EEPROM;
                    end
                end

                S_WAIT_EEPROM: begin
                    if (!i2c_busy) begin
                        if (i2c_ack_error) state <= S_ERROR;
                        else begin
                            captured_data <= i2c_data_out;
                            state <= S_DONE;
                        end
                    end
                end

                S_DONE: begin
                    // Stay here
                end

                S_ERROR: begin
                    // Stay here
                end
                
                default: state <= S_IDLE;
            endcase
        end
    end

endmodule

interface i2c/tb_i2c_system.v
`timescale 1ns / 1ps

module tb_i2c_system;

    reg clk;
    reg rst_n;
    reg start_demo;
    
    wire [7:0] eeprom_data;
    wire demo_done;
    wire error_flag;
    
    wire sda;
    wire scl;

    // Pull-ups for I2C bus (simulated by pulling weak high)
    pullup (sda);
    pullup (scl);

    // Instantiate Top Controller (Master)
    top_controller dut (
        .clk(clk),
        .rst_n(rst_n),
        .start_demo(start_demo),
        .eeprom_data(eeprom_data),
        .demo_done(demo_done),
        .error_flag(error_flag),
        .sda(sda),
        .scl(scl)
    );

    // Instantiate Mock Slave 1 (OLED)
    mock_i2c_slave #(
        .SLAVE_ADDR(7'h3C),
        .READ_DATA(8'h00)
    ) oled_mock (
        .sda(sda),
        .scl(scl)
    );

    // Instantiate Mock Slave 2 (EEPROM)
    mock_i2c_slave #(
        .SLAVE_ADDR(7'h50),
        .READ_DATA(8'h42) // Expected read back value
    ) eeprom_mock (
        .sda(sda),
        .scl(scl)
    );

    // Clock generation (50 MHz)
    initial begin
        clk = 0;
        forever #10 clk = ~clk; 
    end

    // Test sequence
    initial begin
        // Initialize
        rst_n = 0;
        start_demo = 0;
        
        #100;
        rst_n = 1;
        
        #100;
        // Start transaction sequence
        start_demo = 1;
        #20;
        start_demo = 0;

        // Wait for demo to finish
        wait (demo_done == 1'b1 || error_flag == 1'b1);
        
        #1000;
        if (error_flag) begin
            $display("TEST FAILED: I2C transaction error detected.");
        end else if (eeprom_data == 8'h42) begin
            $display("TEST PASSED: EEPROM data read successfully (0x42).");
        end else begin
            $display("TEST FAILED: Incorrect data read from EEPROM: %h", eeprom_data);
        end
        
        $finish;
    end

    // Dump waves
    initial begin
        $dumpfile("i2c_sim.vcd");
        $dumpvars(0, tb_i2c_system);
    end

endmodule

INTERFACE_I2C_BUS.sim/sim_1/behav/xsim/i2c_sim.vcd
$date
   Fri Jun 12 23:18:20 2026
$end

$version
  2025.2
  $dumpfile ("i2c_sim.vcd") 
$end

$timescale
  1ps
$end

$scope module tb_i2c_system $end
$var reg 1 ! clk $end
$var reg 1 " rst_n $end
$var reg 1 # start_demo $end
$var wire 8 $ eeprom_data [7:0] $end
$var wire 1 % demo_done $end
$var wire 1 & error_flag $end
$var wire 1 ' sda $end
$var wire 1 ( scl $end
$scope module dut $end
$var wire 1 ) clk $end
$var wire 1 * rst_n $end
$var wire 1 + start_demo $end
$var wire 8 $ eeprom_data [7:0] $end
$var wire 1 % demo_done $end
$var wire 1 & error_flag $end
$var wire 1 ' sda $end
$var wire 1 ( scl $end
$var reg 1 , i2c_enable $end
$var reg 1 - i2c_rw $end
$var reg 7 . i2c_addr [6:0] $end
$var reg 8 / i2c_data_in [7:0] $end
$var wire 8 0 i2c_data_out [7:0] $end
$var wire 1 1 i2c_busy $end
$var wire 1 2 i2c_ack_error $end
$var reg 4 3 state [3:0] $end
$var reg 8 4 captured_data [7:0] $end
$var reg 16 5 delay_cnt [15:0] $end
$scope module master_inst $end
$var wire 1 ) clk $end
$var wire 1 * rst_n $end
$var wire 1 6 enable $end
$var wire 1 7 rw $end
$var wire 7 8 addr [6:0] $end
$var wire 8 9 data_in [7:0] $end
$var reg 8 : data_out [7:0] $end
$var reg 1 ; busy $end
$var reg 1 < ack_error $end
$var wire 1 ' sda $end
$var wire 1 ( scl $end
$var reg 4 = state [3:0] $end
$var reg 4 > next_state [3:0] $end
$var reg 16 ? clk_count [15:0] $end
$var reg 2 @ i2c_phase [1:0] $end
$var reg 1 A i2c_clk_en $end
$var reg 8 B tx_data [7:0] $end
$var reg 8 C rx_data [7:0] $end
$var reg 3 D bit_count [2:0] $end
$var reg 1 E sda_out $end
$var reg 1 F sda_dir $end
$var reg 1 G scl_out $end
$upscope $end
$upscope $end
$scope module oled_mock $end
$var wire 1 ' sda $end
$var wire 1 ( scl $end
$var reg 8 H shift_reg [7:0] $end
$var reg 4 I bit_count [3:0] $end
$var reg 1 J sda_out $end
$var reg 1 K sda_dir $end
$var reg 1 L is_addressed $end
$var reg 1 M is_read $end
$var reg 8 N start_count [7:0] $end
$var reg 8 O stop_count [7:0] $end
$var reg 8 P last_start_count [7:0] $end
$var reg 8 Q last_stop_count [7:0] $end
$upscope $end
$scope module eeprom_mock $end
$var wire 1 ' sda $end
$var wire 1 ( scl $end
$var reg 8 R shift_reg [7:0] $end
$var reg 4 S bit_count [3:0] $end
$var reg 1 T sda_out $end
$var reg 1 U sda_dir $end
$var reg 1 V is_addressed $end
$var reg 1 W is_read $end
$var reg 8 X start_count [7:0] $end
$var reg 8 Y stop_count [7:0] $end
$var reg 8 Z last_start_count [7:0] $end
$var reg 8 [ last_stop_count [7:0] $end
$upscope $end
$upscope $end
$enddefinitions $end

#0
$dumpvars
0!
0"
0#
b0 $
0%
0&
1'
1(
0)
0*
0+
0,
0-
b0 .
b0 /
b0 0
01
02
b0 3
b0 4
b0 5
06
07
b0 8
b0 9
b0 :
0;
0<
b0 =
bx >
b0 ?
b0 @
0A
b0 B
b0 C
b0 D
1E
1F
1G
b0 H
b0 I
0J
0K
0L
0M
b0 N
b1 O
b0 P
b0 Q
b0 R
b0 S
0T
0U
0V
0W
b0 X
b1 Y
b0 Z
b0 [
$end

#10000
1!
1)

#20000
0!
0)

#30000
1!
1)

#40000
0!
0)

#50000
1!
1)

#60000
0!
0)

#70000
1!
1)

#80000
0!
0)

#90000
1!
1)

#100000
0!
1"
0)
1*

#110000
1!
1)
b1 ?

#120000
0!
0)

#130000
1!
1)
b10 ?

#140000
0!
0)

#150000
1!
1)
b11 ?

#160000
0!
0)

#170000
1!
1)
b100 ?

#180000
0!
0)

#190000
1!
1)
b101 ?

#200000
0!
1#
0)
1+

#210000
1!
1)
1,
b111100 .
b10100101 /
b1 3
16
b111100 8
b10100101 9
b110 ?

#220000
0!
0#
0)
0+

#230000
1!
1)
b111 ?

#240000
0!
0)

#250000
1!
1)
b1000 ?

#260000
0!
0)

#270000
1!
1)
b1001 ?

#280000
0!
0)

#290000
1!
1)
b1010 ?

#300000
0!
0)

#310000
1!
1)
b1011 ?

#320000
0!
0)

#330000
1!
1)
b1100 ?

#340000
0!
0)

#350000
1!
1)
b1101 ?

#360000
0!
0)

#370000
1!
1)
b1110 ?

#380000
0!
0)

#390000
1!
1)
b1111 ?

#400000
0!
0)

#410000
1!
1)
b10000 ?

#420000
0!
0)

#430000
1!
1)
b10001 ?

#440000
0!
0)

#450000
1!
1)
b10010 ?

#460000
0!
0)

#470000
1!
1)
b10011 ?

#480000
0!
0)

#490000
1!
1)
b10100 ?

#500000
0!
0)

#510000
1!
1)
b10101 ?

#520000
0!
0)

#530000
1!
1)
b10110 ?

#540000
0!
0)

#550000
1!
1)
b10111 ?

#560000
0!
0)

#570000
1!
1)
b11000 ?

#580000
0!
0)

#590000
1!
1)
b11001 ?

#600000
0!
0)

#610000
1!
1)
b11010 ?

#620000
0!
0)

#630000
1!
1)
b11011 ?

#640000
0!
0)

#650000
1!
1)
b11100 ?

#660000
0!
0)

#670000
1!
1)
b11101 ?

#680000
0!
0)

#690000
1!
1)
b11110 ?

#700000
0!
0)

#710000
1!
1)
b11111 ?

#720000
0!
0)

#730000
1!
1)
b100000 ?

#740000
0!
0)

#750000
1!
1)
b100001 ?

#760000
0!
0)

#770000
1!
1)
b100010 ?

#780000
0!
0)

#790000
1!
1)
b100011 ?

#800000
0!
0)

#810000
1!
1)
b100100 ?

#820000
0!
0)

#830000
1!
1)
b100101 ?

#840000
0!
0)

#850000
1!
1)
b100110 ?

#860000
0!
0)

#870000
1!
1)
b100111 ?

#880000
0!
0)

#890000
1!
1)
b101000 ?

#900000
0!
0)

#910000
1!
1)
b101001 ?

#920000
0!
0)

#930000
1!
1)
b101010 ?

#940000
0!
0)

#950000
1!
1)
b101011 ?

#960000
0!
0)

#970000
1!
1)
b101100 ?

#980000
0!
0)

#990000
1!
1)
b101101 ?

#1000000
0!
0)

#1010000
1!
1)
b101110 ?

#1020000
0!
0)

#1030000
1!
1)
b101111 ?

#1040000
0!
0)

#1050000
1!
1)
b110000 ?

#1060000
0!
0)

#1070000
1!
1)
b110001 ?

#1080000
0!
0)

#1090000
1!
1)
b110010 ?

#1100000
0!
0)

#1110000
1!
1)
b110011 ?

#1120000
0!
0)

#1130000
1!
1)
b110100 ?

#1140000
0!
0)

#1150000
1!
1)
b110101 ?

#1160000
0!
0)

#1170000
1!
1)
b110110 ?

#1180000
0!
0)

#1190000
1!
1)
b110111 ?

#1200000
0!
0)

#1210000
1!
1)
b111000 ?

#1220000
0!
0)

#1230000
1!
1)
b111001 ?

#1240000
0!
0)

#1250000
1!
1)
b111010 ?

#1260000
0!
0)

#1270000
1!
1)
b111011 ?

#1280000
0!
0)

#1290000
1!
1)
b111100 ?

#1300000
0!
0)

#1310000
1!
1)
b111101 ?

#1320000
0!
0)

#1330000
1!
1)
b111110 ?

#1340000
0!
0)

#1350000
1!
1)
b111111 ?

#1360000
0!
0)

#1370000
1!
1)
b1000000 ?

#1380000
0!
0)

#1390000
1!
1)
b1000001 ?

#1400000
0!
0)

#1410000
1!
1)
b1000010 ?

#1420000
0!
0)

#1430000
1!
1)
b1000011 ?

#1440000
0!
0)

#1450000
1!
1)
b1000100 ?

#1460000
0!
0)

#1470000
1!
1)
b1000101 ?

#1480000
0!
0)

#1490000
1!
1)
b1000110 ?

#1500000
0!
0)

#1510000
1!
1)
b1000111 ?

#1520000
0!
0)

#1530000
1!
1)
b1001000 ?

#1540000
0!
0)

#1550000
1!
1)
b1001001 ?

#1560000
0!
0)

#1570000
1!
1)
b1001010 ?

#1580000
0!
0)

#1590000
1!
1)
b1001011 ?

#1600000
0!
0)

#1610000
1!
1)
b1001100 ?

#1620000
0!
0)

#1630000
1!
1)
b1001101 ?

#1640000
0!
0)

#1650000
1!
1)
b1001110 ?

#1660000
0!
0)

#1670000
1!
1)
b1001111 ?

#1680000
0!
0)

#1690000
1!
1)
b1010000 ?

#1700000
0!
0)

#1710000
1!
1)
b1010001 ?

#1720000
0!
0)

#1730000
1!
1)
b1010010 ?

#1740000
0!
0)

#1750000
1!
1)
b1010011 ?

#1760000
0!
0)

#1770000
1!
1)
b1010100 ?

#1780000
0!
0)

#1790000
1!
1)
b1010101 ?

#1800000
0!
0)

#1810000
1!
1)
b1010110 ?

#1820000
0!
0)

#1830000
1!
1)
b1010111 ?

#1840000
0!
0)

#1850000
1!
1)
b1011000 ?

#1860000
0!
0)

#1870000
1!
1)
b1011001 ?

#1880000
0!
0)

#1890000
1!
1)
b1011010 ?

#1900000
0!
0)

#1910000
1!
1)
b1011011 ?

#1920000
0!
0)

#1930000
1!
1)
b1011100 ?

#1940000
0!
0)

#1950000
1!
1)
b1011101 ?

#1960000
0!
0)

#1970000
1!
1)
b1011110 ?

#1980000
0!
0)

#1990000
1!
1)
b1011111 ?

#2000000
0!
0)

#2010000
1!
1)
b1100000 ?

#2020000
0!
0)

#2030000
1!
1)
b1100001 ?

#2040000
0!
0)

#2050000
1!
1)
b1100010 ?

#2060000
0!
0)

#2070000
1!
1)
b1100011 ?

#2080000
0!
0)

#2090000
1!
1)
b1100100 ?

#2100000
0!
0)

#2110000
1!
1)
b1100101 ?

#2120000
0!
0)

#2130000
1!
1)
b1100110 ?

#2140000
0!
0)

#2150000
1!
1)
b1100111 ?

#2160000
0!
0)

#2170000
1!
1)
b1101000 ?

#2180000
0!
0)

#2190000
1!
1)
b1101001 ?

#2200000
0!
0)

#2210000
1!
1)
b1101010 ?

#2220000
0!
0)

#2230000
1!
1)
b1101011 ?

#2240000
0!
0)

#2250000
1!
1)
b1101100 ?

#2260000
0!
0)

#2270000
1!
1)
b1101101 ?

#2280000
0!
0)

#2290000
1!
1)
b1101110 ?

#2300000
0!
0)

#2310000
1!
1)
b1101111 ?

#2320000
0!
0)

#2330000
1!
1)
b1110000 ?

#2340000
0!
0)

#2350000
1!
1)
b1110001 ?

#2360000
0!
0)

#2370000
1!
1)
b1110010 ?

#2380000
0!
0)

#2390000
1!
1)
b1110011 ?

#2400000
0!
0)

#2410000
1!
1)
b1110100 ?

#2420000
0!
0)

#2430000
1!
1)
b1110101 ?

#2440000
0!
0)

#2450000
1!
1)
b1110110 ?

#2460000
0!
0)

#2470000
1!
1)
b1110111 ?

#2480000
0!
0)

#2490000
1!
1)
b1111000 ?

#2500000
0!
0)

#2510000
1!
1)
b1111001 ?

#2520000
0!
0)

#2530000
1!
1)
b1111010 ?

#2540000
0!
0)

#2550000
1!
1)
b1111011 ?

#2560000
0!
0)

#2570000
1!
1)
b1111100 ?

#2580000
0!
0)

#2590000
1!
1)
b0 ?
b1 @
1A

#2600000
0!
0)

#2610000
1!
1)
11
1;
b1 =
b1 ?
0A
b1111000 B

#2620000
0!
0)

#2630000
1!
1)
0,
b10 3
06
b10 ?

#2640000
0!
0)

#2650000
1!
1)
b11 ?

#2660000
0!
0)

#2670000
1!
1)
b100 ?

#2680000
0!
0)

#2690000
1!
1)
b101 ?

#2700000
0!
0)

#2710000
1!
1)
b110 ?

#2720000
0!
0)

#2730000
1!
1)
b111 ?

#2740000
0!
0)

#2750000
1!
1)
b1000 ?

#2760000
0!
0)

#2770000
1!
1)
b1001 ?

#2780000
0!
0)

#2790000
1!
1)
b1010 ?

#2800000
0!
0)

#2810000
1!
1)
b1011 ?

#2820000
0!
0)

#2830000
1!
1)
b1100 ?

#2840000
0!
0)

#2850000
1!
1)
b1101 ?

#2860000
0!
0)

#2870000
1!
1)
b1110 ?

#2880000
0!
0)

#2890000
1!
1)
b1111 ?

#2900000
0!
0)

#2910000
1!
1)
b10000 ?

#2920000
0!
0)

#2930000
1!
1)
b10001 ?

#2940000
0!
0)

#2950000
1!
1)
b10010 ?

#2960000
0!
0)

#2970000
1!
1)
b10011 ?

#2980000
0!
0)

#2990000
1!
1)
b10100 ?

#3000000
0!
0)

#3010000
1!
1)
b10101 ?

#3020000
0!
0)

#3030000
1!
1)
b10110 ?

#3040000
0!
0)

#3050000
1!
1)
b10111 ?

#3060000
0!
0)

#3070000
1!
1)
b11000 ?

#3080000
0!
0)

#3090000
1!
1)
b11001 ?

#3100000
0!
0)

#3110000
1!
1)
b11010 ?

#3120000
0!
0)

#3130000
1!
1)
b11011 ?

#3140000
0!
0)

#3150000
1!
1)
b11100 ?

#3160000
0!
0)

#3170000
1!
1)
b11101 ?

#3180000
0!
0)

#3190000
1!
1)
b11110 ?

#3200000
0!
0)

#3210000
1!
1)
b11111 ?

#3220000
0!
0)

#3230000
1!
1)
b100000 ?

#3240000
0!
0)

#3250000
1!
1)
b100001 ?

#3260000
0!
0)

#3270000
1!
1)
b100010 ?

#3280000
0!
0)

#3290000
1!
1)
b100011 ?

#3300000
0!
0)

#3310000
1!
1)
b100100 ?

#3320000
0!
0)

#3330000
1!
1)
b100101 ?

#3340000
0!
0)

#3350000
1!
1)
b100110 ?

#3360000
0!
0)

#3370000
1!
1)
b100111 ?

#3380000
0!
0)

#3390000
1!
1)
b101000 ?

#3400000
0!
0)

#3410000
1!
1)
b101001 ?

#3420000
0!
0)

#3430000
1!
1)
b101010 ?

#3440000
0!
0)

#3450000
1!
1)
b101011 ?

#3460000
0!
0)

#3470000
1!
1)
b101100 ?

#3480000
0!
0)

#3490000
1!
1)
b101101 ?

#3500000
0!
0)

#3510000
1!
1)
b101110 ?

#3520000
0!
0)

#3530000
1!
1)
b101111 ?

#3540000
0!
0)

#3550000
1!
1)
b110000 ?

#3560000
0!
0)

#3570000
1!
1)
b110001 ?

#3580000
0!
0)

#3590000
1!
1)
b110010 ?

#3600000
0!
0)

#3610000
1!
1)
b110011 ?

#3620000
0!
0)

#3630000
1!
1)
b110100 ?

#3640000
0!
0)

#3650000
1!
1)
b110101 ?

#3660000
0!
0)

#3670000
1!
1)
b110110 ?

#3680000
0!
0)

#3690000
1!
1)
b110111 ?

#3700000
0!
0)

#3710000
1!
1)
b111000 ?

#3720000
0!
0)

#3730000
1!
1)
b111001 ?

#3740000
0!
0)

#3750000
1!
1)
b111010 ?

#3760000
0!
0)

#3770000
1!
1)
b111011 ?

#3780000
0!
0)

#3790000
1!
1)
b111100 ?

#3800000
0!
0)

#3810000
1!
1)
b111101 ?

#3820000
0!
0)

#3830000
1!
1)
b111110 ?

#3840000
0!
0)

#3850000
1!
1)
b111111 ?

#3860000
0!
0)

#3870000
1!
1)
b1000000 ?

#3880000
0!
0)

#3890000
1!
1)
b1000001 ?

#3900000
0!
0)

#3910000
1!
1)
b1000010 ?

#3920000
0!
0)

#3930000
1!
1)
b1000011 ?

#3940000
0!
0)

#3950000
1!
1)
b1000100 ?

#3960000
0!
0)

#3970000
1!
1)
b1000101 ?

#3980000
0!
0)

#3990000
1!
1)
b1000110 ?

#4000000
0!
0)

#4010000
1!
1)
b1000111 ?

#4020000
0!
0)

#4030000
1!
1)
b1001000 ?

#4040000
0!
0)

#4050000
1!
1)
b1001001 ?

#4060000
0!
0)

#4070000
1!
1)
b1001010 ?

#4080000
0!
0)

#4090000
1!
1)
b1001011 ?

#4100000
0!
0)

#4110000
1!
1)
b1001100 ?

#4120000
0!
0)

#4130000
1!
1)
b1001101 ?

#4140000
0!
0)

#4150000
1!
1)
b1001110 ?

#4160000
0!
0)

#4170000
1!
1)
b1001111 ?

#4180000
0!
0)

#4190000
1!
1)
b1010000 ?

