interface i2c/i2c_slave.v
`timescale 1ns / 1ps

// ============================================================
// i2c_slave.v  –  Fixed behavioral I2C slave (simulation only)
//
// Fixes vs previous version:
//   1. start/stop detection uses counters (no multiple-driver).
//   2. shift_reg samples on posedge SCL (data stable during SCL HIGH).
//   3. Address phase: bit_count increments on negedge SCL after capture.
//   4. ACK released correctly after address + data phases.
//   5. READ data phase starts from bit 7 after ACK (bit_count reset to 0).
//   6. WRITE data ACK at correct bit position (bit 8).
// ============================================================
module i2c_slave #(
    parameter SLAVE_ADDR = 7'h3C,
    parameter READ_DATA  = 8'hBB
)(
    inout wire sda,
    input wire scl
);

    // ---- SDA tri-state driver ----
    reg sda_out = 1'b1;
    reg sda_dir = 1'b0;    // 1 = slave drives, 0 = slave releases
    assign sda = (sda_dir) ? sda_out : 1'bz;

    // ---- State registers ----
    reg [7:0] shift_reg   = 8'h00;
    reg [3:0] bit_count   = 4'h0;
    reg       is_addressed= 1'b0;
    reg       is_read     = 1'b0;

    // ====================================================================
    // START / STOP detection using counters (no multiple-driver issue)
    // start_count increments on every SDA-falling-while-SCL-HIGH event.
    // stop_count  increments on every SDA-rising-while-SCL-HIGH event.
    // The negedge-SCL state machine compares to shadow copies to detect
    // new START / STOP events without racing with the SDA-edge blocks.
    // ====================================================================
    reg [7:0] start_count      = 8'h00;
    reg [7:0] stop_count       = 8'h00;
    reg [7:0] last_start_count = 8'h00;
    reg [7:0] last_stop_count  = 8'h00;

    always @(negedge sda) begin
        if (scl === 1'b1) start_count <= start_count + 1;
    end

    always @(posedge sda) begin
        if (scl === 1'b1) stop_count <= stop_count + 1;
    end

    // ====================================================================
    // DATA SAMPLING  – posedge SCL captures SDA into shift_reg / is_read
    // (SDA is stable during SCL HIGH per I2C spec)
    // ====================================================================
    always @(posedge scl) begin
        if (!is_addressed) begin
            // Address phase: collect 7 addr bits then the R/W bit
            if (bit_count < 4'd7)
                shift_reg[6 - bit_count] <= sda;   // MSB first → [6],[5]...[0]
            else if (bit_count == 4'd7)
                is_read <= sda;                     // 8th bit = R/W
        end else begin
            // Data phase (WRITE): master sends data, slave receives
            if (!is_read && bit_count < 4'd8)
                shift_reg[7 - bit_count] <= sda;   // MSB first
        end
    end

    // ====================================================================
    // STATE MACHINE  – runs on negedge SCL (after master has clocked bit)
    // ====================================================================
    always @(negedge scl) begin

        // ---- START detected since last negedge SCL? ----
        if (start_count != last_start_count) begin
            last_start_count <= start_count;
            bit_count    <= 4'd0;
            sda_dir      <= 1'b0;
            is_addressed <= 1'b0;

        // ---- STOP detected since last negedge SCL? ----
        end else if (stop_count != last_stop_count) begin
            last_stop_count <= stop_count;
            sda_dir      <= 1'b0;
            is_addressed <= 1'b0;

        // ---- Normal bit clock ----
        end else begin

            if (!is_addressed) begin
                // ---- ADDRESS PHASE ----
                // Bits are sampled on posedge SCL above.
                // After 8 posedge SCL (7 addr + 1 RW), we have full info.
                // bit_count here reflects how many negedge SCL we've seen.

                if (bit_count < 4'd7) begin
                    // Still capturing address bits
                    bit_count <= bit_count + 1;

                end else if (bit_count == 4'd7) begin
                    // All 8 bits captured (addr + RW) — decide ACK/NACK
                    $display("[%0t ns] SLAVE 0x%02h: received addr byte, shift_reg=0x%02h is_read=%b",
                             $time, SLAVE_ADDR, {shift_reg[6:0], is_read}, is_read);

                    if (shift_reg[6:0] == SLAVE_ADDR) begin
                        $display("[%0t ns] SLAVE 0x%02h: ADDRESS MATCH — sending ACK", $time, SLAVE_ADDR);
                        sda_dir <= 1'b1;
                        sda_out <= 1'b0;  // pull SDA LOW = ACK
                    end else begin
                        $display("[%0t ns] SLAVE 0x%02h: no match (got 0x%02h) — NACK",
                                 $time, SLAVE_ADDR, shift_reg[6:0]);
                        sda_dir <= 1'b0;  // release SDA = NACK
                    end
                    bit_count <= bit_count + 1;

                end else if (bit_count == 4'd8) begin
                    // ACK/NACK has been clocked — release SDA, go to data phase
                    sda_dir      <= 1'b0;
                    bit_count    <= 4'd0;
                    if (shift_reg[6:0] == SLAVE_ADDR) begin
                        is_addressed <= 1'b1;
                        // If READ: pre-load shift_reg with data to transmit
                        if (is_read)
                            shift_reg <= READ_DATA;
                    end
                end

            end else begin
                // ---- DATA PHASE ----

                if (is_read) begin
                    // ---- SLAVE TRANSMITS (master reads) ----
                    if (bit_count < 4'd8) begin
                        sda_dir <= 1'b1;
                        sda_out <= shift_reg[7 - bit_count];   // MSB first
                        bit_count <= bit_count + 1;
                    end else begin
                        // All 8 bits sent — release for master NACK/ACK
                        sda_dir      <= 1'b0;
                        bit_count    <= 4'd0;
                        is_addressed <= 1'b0;
                    end

                end else begin
                    // ---- SLAVE RECEIVES (master writes) ----
                    // Data bits captured by posedge-SCL block above.
                    if (bit_count < 4'd8) begin
                        bit_count <= bit_count + 1;
                    end else if (bit_count == 4'd8) begin
                        // Send ACK for received data byte
                        sda_dir <= 1'b1;
                        sda_out <= 1'b0;        // ACK
                        bit_count <= bit_count + 1;
                    end else begin
                        // Done — release SDA
                        sda_dir      <= 1'b0;
                        bit_count    <= 4'd0;
                        is_addressed <= 1'b0;
                    end
                end
            end
        end
    end

endmodule

interface i2c/i2c_master.v
`timescale 1ns / 1ps

module i2c_master #(
    parameter INPUT_CLK_FREQ = 50_000_000, // 50 MHz default
    parameter I2C_FREQ       = 100_000     // 100 kHz I2C clock
)(
    input  wire       clk,
    input  wire       rst_n,
    
    // Control interface
    input  wire       enable,      // Pulse high to start transaction
    input  wire       rw,          // 0 = write, 1 = read
    input  wire [6:0] addr,        // 7-bit target address
    input  wire [7:0] data_in,     // Data to write
    output reg  [7:0] data_out,    // Data read
    output reg        busy,        // High while transaction is ongoing
    output reg        ack_error,   // High if slave NACKs
    
    // I2C bus signals
    inout  wire       sda,
    output wire       scl
);

    // Derived parameters
    localparam DIVIDER = (INPUT_CLK_FREQ / I2C_FREQ) / 4; 
    // We divide by 4 because an I2C clock cycle has 4 phases: SCL low, SCL low-to-high, SCL high, SCL high-to-low

    // State Machine
    localparam IDLE    = 4'd0;
    localparam START   = 4'd1;
    localparam ADDR    = 4'd2;
    localparam ACK1    = 4'd3;
    localparam WRITE   = 4'd4;
    localparam READ    = 4'd5;
    localparam ACK2    = 4'd6;
    localparam STOP    = 4'd7;

    reg [3:0] state, next_state;
    reg [15:0] clk_count;
    reg [1:0]  i2c_phase;  // 00: SCL=0, 01: SCL=1 edge, 10: SCL=1, 11: SCL=0 edge
    reg i2c_clk_en;

    reg [7:0] tx_data;
    reg [7:0] rx_data;
    reg [2:0] bit_count;

    reg sda_out, sda_dir, scl_out;
    
    // Tri-state buffer for SDA
    assign sda = (sda_dir == 1'b1) ? sda_out : 1'bz;
    assign scl = scl_out;

    // Clock divider
    always @(posedge clk or negedge rst_n) begin
        if (!rst_n) begin
            clk_count <= 0;
            i2c_phase <= 0;
            i2c_clk_en <= 0;
        end else begin
            if (clk_count == DIVIDER - 1) begin
                clk_count <= 0;
                i2c_phase <= i2c_phase + 1;
                i2c_clk_en <= 1'b1;
            end else begin
                clk_count <= clk_count + 1;
                i2c_clk_en <= 1'b0;
            end
        end
    end

    // FSM sequential logic
    always @(posedge clk or negedge rst_n) begin
        if (!rst_n) begin
            state <= IDLE;
            busy <= 0;
            ack_error <= 0;
            bit_count <= 0;
            tx_data <= 0;
            rx_data <= 0;
            data_out <= 0;
            sda_out <= 1;
            sda_dir <= 1;
            scl_out <= 1;
        end else begin
            if (i2c_clk_en) begin
                case (state)
                    IDLE: begin
                        sda_out <= 1;
                        sda_dir <= 1;
                        scl_out <= 1;
                        busy <= 0;
                        if (enable) begin
                            state <= START;
                            tx_data <= {addr, rw};
                            busy <= 1;
                            ack_error <= 0;
                        end
                    end

                    START: begin
                        busy <= 1;
                        case (i2c_phase)
                            2'b00: begin sda_out <= 1; sda_dir <= 1; scl_out <= 1; end
                            2'b01: begin sda_out <= 1; scl_out <= 1; end
                            2'b10: begin sda_out <= 0; scl_out <= 1; end
                            2'b11: begin sda_out <= 0; scl_out <= 0; end
                        endcase
                        if (i2c_phase == 2'b11) begin
                            state <= ADDR;
                            bit_count <= 7;
                        end
                    end

                    ADDR: begin
                        case (i2c_phase)
                            2'b00: begin sda_dir <= 1; sda_out <= tx_data[bit_count]; scl_out <= 0; end
                            2'b01: scl_out <= 1;
                            2'b10: scl_out <= 1;
                            2'b11: scl_out <= 0;
                        endcase
                        if (i2c_phase == 2'b11) begin
                            if (bit_count == 0) state <= ACK1;
                            else bit_count <= bit_count - 1;
                        end
                    end

                    ACK1: begin
                        case (i2c_phase)
                            2'b00: begin sda_dir <= 0; scl_out <= 0; end // Release SDA for slave ACK
                            2'b01: scl_out <= 1;
                            2'b10: begin scl_out <= 1; ack_error <= sda; end // Sample ACK
                            2'b11: scl_out <= 0;
                        endcase
                        if (i2c_phase == 2'b11) begin
                            if (ack_error) begin
                                state <= STOP; // Stop on NACK
                            end else begin
                                bit_count <= 7;
                                if (rw == 0) begin // Write
                                    tx_data <= data_in;
                                    state <= WRITE;
                                end else begin // Read
                                    state <= READ;
                                end
                            end
                        end
                    end

                    WRITE: begin
                        case (i2c_phase)
                            2'b00: begin sda_dir <= 1; sda_out <= tx_data[bit_count]; scl_out <= 0; end
                            2'b01: scl_out <= 1;
                            2'b10: scl_out <= 1;
                            2'b11: scl_out <= 0;
                        endcase
                        if (i2c_phase == 2'b11) begin
                            if (bit_count == 0) state <= ACK2;
                            else bit_count <= bit_count - 1;
                        end
                    end

                    READ: begin
                        case (i2c_phase)
                            2'b00: begin sda_dir <= 0; scl_out <= 0; end // Release SDA to read
                            2'b01: scl_out <= 1;
                            2'b10: begin scl_out <= 1; rx_data[bit_count] <= sda; end // Sample Data
                            2'b11: scl_out <= 0;
                        endcase
                        if (i2c_phase == 2'b11) begin
                            if (bit_count == 0) begin
                                data_out <= rx_data;
                                state <= ACK2;
                            end else begin
                                bit_count <= bit_count - 1;
                            end
                        end
                    end

                    ACK2: begin
                        case (i2c_phase)
                            2'b00: begin 
                                if (rw == 0) begin
                                    sda_dir <= 0; // Wait for slave ACK if we wrote
                                end else begin
                                    sda_dir <= 1; sda_out <= 1; // Master NACK after read (for 1 byte read)
                                end
                                scl_out <= 0; 
                            end
                            2'b01: scl_out <= 1;
                            2'b10: begin 
                                scl_out <= 1; 
                                if (rw == 0) ack_error <= sda; // Check ACK from slave
                            end 
                            2'b11: scl_out <= 0;
                        endcase
                        if (i2c_phase == 2'b11) begin
                            state <= STOP;
                        end
                    end

                    STOP: begin
                        case (i2c_phase)
                            2'b00: begin sda_dir <= 1; sda_out <= 0; scl_out <= 0; end
                            2'b01: begin scl_out <= 1; end
                            2'b10: begin sda_out <= 1; scl_out <= 1; end // SDA low to high while SCL is high -> STOP
                            2'b11: begin sda_out <= 1; scl_out <= 1; end
                        endcase
                        if (i2c_phase == 2'b11) begin
                            state <= IDLE;
                            busy <= 0;
                        end
                    end

                    default: state <= IDLE;
                endcase
            end
        end
    end

endmodule

INTERFACE_I2C_BUS.srcs/sources_1/imports/interface i2c/top_controller.v
`timescale 1ns / 1ps

module top_controller (
    input  wire       clk,
    input  wire       rst_n,
    input  wire       start_demo,
    
    // Outputs to observe states
    output wire [7:0] eeprom_data,
    output wire       demo_done,
    output wire       error_flag,
    
    // I2C bus
    inout  wire       sda,
    output wire       scl
);

    // I2C Master Interface
    reg        i2c_enable;
    reg        i2c_rw;
    reg  [6:0] i2c_addr;
    reg  [7:0] i2c_data_in;
    wire [7:0] i2c_data_out;
    wire       i2c_busy;
    wire       i2c_ack_error;
    
    i2c_master #(
        .INPUT_CLK_FREQ(50_000_000),
        .I2C_FREQ(100_000)
    ) master_inst (
        .clk(clk),
        .rst_n(rst_n),
        .enable(i2c_enable),
        .rw(i2c_rw),
        .addr(i2c_addr),
        .data_in(i2c_data_in),
        .data_out(i2c_data_out),
        .busy(i2c_busy),
        .ack_error(i2c_ack_error),
        .sda(sda),
        .scl(scl)
    );

    // FSM States
    localparam S_IDLE            = 0;
    localparam S_WRITE_OLED      = 1;
    localparam S_WAIT_OLED       = 2;
    localparam S_DELAY           = 3; // Delay between transactions
    localparam S_WRITE_EEPROM_ADDR = 4;
    localparam S_WAIT_EEPROM_ADDR = 5;
    localparam S_READ_EEPROM     = 6;
    localparam S_WAIT_EEPROM     = 7;
    localparam S_DONE            = 8;
    localparam S_ERROR           = 9;

    reg [3:0] state;
    reg [7:0] captured_data;
    reg [15:0] delay_cnt;
    
    assign eeprom_data = captured_data;
    assign demo_done = (state == S_DONE);
    assign error_flag = (state == S_ERROR);

    always @(posedge clk or negedge rst_n) begin
        if (!rst_n) begin
            state <= S_IDLE;
            i2c_enable <= 0;
            i2c_rw <= 0;
            i2c_addr <= 0;
            i2c_data_in <= 0;
            captured_data <= 0;
            delay_cnt <= 0;
        end else begin
            case (state)
                S_IDLE: begin
                    i2c_enable <= 0;
                    if (start_demo && !i2c_busy) begin
                        // Start by writing to OLED (0x3C)
                        state <= S_WRITE_OLED;
                        i2c_addr <= 7'h3C;
                        i2c_rw <= 0;
                        i2c_data_in <= 8'hA5; // dummy data
                        i2c_enable <= 1;
                    end
                end

                S_WRITE_OLED: begin
                    if (i2c_busy) begin
                        i2c_enable <= 0;
                        state <= S_WAIT_OLED;
                    end
                end

                S_WAIT_OLED: begin
                    if (!i2c_busy) begin
                        if (i2c_ack_error) state <= S_ERROR;
                        else begin
                            state <= S_DELAY;
                            delay_cnt <= 0;
                        end
                    end
                end

                S_DELAY: begin
                    if (delay_cnt == 16'hFFFF) begin
                        state <= S_WRITE_EEPROM_ADDR;
                        i2c_addr <= 7'h50; // EEPROM address
                        i2c_rw <= 0;
                        i2c_data_in <= 8'h00; // Memory address 0x00
                        i2c_enable <= 1;
                    end else begin
                        delay_cnt <= delay_cnt + 1;
                    end
                end

                S_WRITE_EEPROM_ADDR: begin
                    if (i2c_busy) begin
                        i2c_enable <= 0;
                        state <= S_WAIT_EEPROM_ADDR;
                    end
                end

                S_WAIT_EEPROM_ADDR: begin
                    if (!i2c_busy) begin
                        if (i2c_ack_error) state <= S_ERROR;
                        else begin
                            state <= S_READ_EEPROM;
                            i2c_addr <= 7'h50;
                            i2c_rw <= 1; // READ mode
                            i2c_enable <= 1;
                        end
                    end
                end

                S_READ_EEPROM: begin
                    if (i2c_busy) begin
                        i2c_enable <= 0;
                        state <= S_WAIT_EEPROM;
                    end
                end

                S_WAIT_EEPROM: begin
                    if (!i2c_busy) begin
                        if (i2c_ack_error) state <= S_ERROR;
                        else begin
                            captured_data <= i2c_data_out;
                            state <= S_DONE;
                        end
                    end
                end

                S_DONE: begin
                    // Stay here
                end

                S_ERROR: begin
                    // Stay here
                end
                
                default: state <= S_IDLE;
            endcase
        end
    end

endmodule

INTERFACE_I2C_BUS.srcs/sources_1/imports/interface i2c/tb_i2c_system.v
`timescale 1ns / 1ps

module tb_i2c_system;

    reg clk;
    reg rst_n;
    reg start_demo;
    
    wire [7:0] eeprom_data;
    wire demo_done;
    wire error_flag;
    
    wire sda;
    wire scl;

    // Pull-ups for I2C bus (simulated by pulling weak high)
    pullup (sda);
    pullup (scl);

    // Instantiate Top Controller (Master)
    top_controller dut (
        .clk(clk),
        .rst_n(rst_n),
        .start_demo(start_demo),
        .eeprom_data(eeprom_data),
        .demo_done(demo_done),
        .error_flag(error_flag),
        .sda(sda),
        .scl(scl)
    );

    // I2C Devices on the bus:
    // Instantiate OLED Display Slave (Address: 0x3C)
    i2c_slave #(
        .SLAVE_ADDR(7'h3C),
        .READ_DATA(8'h00)
    ) oled_slave (
        .sda(sda),
        .scl(scl)
    );

    // Instantiate EEPROM Slave (Address: 0x50)
    // Setup to return 0x42 when read
    i2c_slave #(
        .SLAVE_ADDR(7'h50),
        .READ_DATA(8'h42)
    ) eeprom_slave (
        .sda(sda),
        .scl(scl)
    );
    // Clock generation (50 MHz)
    initial begin
        clk = 0;
        forever #10 clk = ~clk; 
    end

    // Test sequence
    initial begin
        // Initialize
        rst_n = 0;
        start_demo = 0;
        
        #100;
        rst_n = 1;
        
        #100;
        // Start transaction sequence
        start_demo = 1;
        #20;
        start_demo = 0;

        // Wait for demo to finish
        wait (demo_done == 1'b1 || error_flag == 1'b1);
        
        #1000;
        if (error_flag) begin
            $display("TEST FAILED: I2C transaction error detected.");
        end else if (eeprom_data == 8'h42) begin
            $display("TEST PASSED: EEPROM data read successfully (0x42).");
        end else begin
            $display("TEST FAILED: Incorrect data read from EEPROM: %h", eeprom_data);
        end
        
        $finish;
    end

    // Dump waves
    initial begin
        $dumpfile("i2c_sim.vcd");
        $dumpvars(0, tb_i2c_system);
    end

endmodule

INTERFACE_I2C_BUS.sim/sim_1/behav/xsim/i2c_sim.vcd
$date
   Thu Jun 18 15:44:16 2026
$end

$version
  2025.2
  $dumpfile ("i2c_sim.vcd") 
$end

$timescale
  1ps
$end

$scope module tb_i2c_system $end
$var reg 1 ! clk $end
$var reg 1 " rst_n $end
$var reg 1 # start_demo $end
$var wire 8 $ eeprom_data [7:0] $end
$var wire 1 % demo_done $end
$var wire 1 & error_flag $end
$var wire 1 ' sda $end
$var wire 1 ( scl $end
$scope module dut $end
$var wire 1 ) clk $end
$var wire 1 * rst_n $end
$var wire 1 + start_demo $end
$var wire 8 $ eeprom_data [7:0] $end
$var wire 1 % demo_done $end
$var wire 1 & error_flag $end
$var wire 1 ' sda $end
$var wire 1 ( scl $end
$var reg 1 , i2c_enable $end
$var reg 1 - i2c_rw $end
$var reg 7 . i2c_addr [6:0] $end
$var reg 8 / i2c_data_in [7:0] $end
$var wire 8 0 i2c_data_out [7:0] $end
$var wire 1 1 i2c_busy $end
$var wire 1 2 i2c_ack_error $end
$var reg 4 3 state [3:0] $end
$var reg 8 4 captured_data [7:0] $end
$var reg 16 5 delay_cnt [15:0] $end
$scope module master_inst $end
$var wire 1 ) clk $end
$var wire 1 * rst_n $end
$var wire 1 6 enable $end
$var wire 1 7 rw $end
$var wire 7 8 addr [6:0] $end
$var wire 8 9 data_in [7:0] $end
$var reg 8 : data_out [7:0] $end
$var reg 1 ; busy $end
$var reg 1 < ack_error $end
$var wire 1 ' sda $end
$var wire 1 ( scl $end
$var reg 4 = state [3:0] $end
$var reg 4 > next_state [3:0] $end
$var reg 16 ? clk_count [15:0] $end
$var reg 2 @ i2c_phase [1:0] $end
$var reg 1 A i2c_clk_en $end
$var reg 8 B tx_data [7:0] $end
$var reg 8 C rx_data [7:0] $end
$var reg 3 D bit_count [2:0] $end
$var reg 1 E sda_out $end
$var reg 1 F sda_dir $end
$var reg 1 G scl_out $end
$upscope $end
$upscope $end
$scope module oled_slave $end
$var wire 1 ' sda $end
$var wire 1 ( scl $end
$var reg 8 H shift_reg [7:0] $end
$var reg 4 I bit_count [3:0] $end
$var reg 1 J sda_out $end
$var reg 1 K sda_dir $end
$var reg 1 L is_addressed $end
$var reg 1 M is_read $end
$var reg 8 N start_count [7:0] $end
$var reg 8 O stop_count [7:0] $end
$var reg 8 P last_start_count [7:0] $end
$var reg 8 Q last_stop_count [7:0] $end
$upscope $end
$scope module eeprom_slave $end
$var wire 1 ' sda $end
$var wire 1 ( scl $end
$var reg 8 R shift_reg [7:0] $end
$var reg 4 S bit_count [3:0] $end
$var reg 1 T sda_out $end
$var reg 1 U sda_dir $end
$var reg 1 V is_addressed $end
$var reg 1 W is_read $end
$var reg 8 X start_count [7:0] $end
$var reg 8 Y stop_count [7:0] $end
$var reg 8 Z last_start_count [7:0] $end
$var reg 8 [ last_stop_count [7:0] $end
$upscope $end
$upscope $end
$enddefinitions $end

#0
$dumpvars
0!
0"
0#
b0 $
0%
0&
1'
1(
0)
0*
0+
0,
0-
b0 .
b0 /
b0 0
01
02
b0 3
b0 4
b0 5
06
07
b0 8
b0 9
b0 :
0;
0<
b0 =
bx >
b0 ?
b0 @
0A
b0 B
b0 C
b0 D
1E
1F
1G
b1000000 H
b0 I
0J
0K
0L
0M
b0 N
b1 O
b0 P
b0 Q
b1000000 R
b0 S
0T
0U
0V
0W
b0 X
b1 Y
b0 Z
b0 [
$end

#10000
1!
1)

#20000
0!
0)

#30000
1!
1)

#40000
0!
0)

#50000
1!
1)

#60000
0!
0)

#70000
1!
1)

#80000
0!
0)

#90000
1!
1)

#100000
0!
1"
0)
1*

#110000
1!
1)
b1 ?

#120000
0!
0)

#130000
1!
1)
b10 ?

#140000
0!
0)

#150000
1!
1)
b11 ?

#160000
0!
0)

#170000
1!
1)
b100 ?

#180000
0!
0)

#190000
1!
1)
b101 ?

#200000
0!
1#
0)
1+

#210000
1!
1)
1,
b111100 .
b10100101 /
b1 3
16
b111100 8
b10100101 9
b110 ?

#220000
0!
0#
0)
0+

#230000
1!
1)
b111 ?

#240000
0!
0)

#250000
1!
1)
b1000 ?

#260000
0!
0)

#270000
1!
1)
b1001 ?

#280000
0!
0)

#290000
1!
1)
b1010 ?

#300000
0!
0)

#310000
1!
1)
b1011 ?

#320000
0!
0)

#330000
1!
1)
b1100 ?

#340000
0!
0)

#350000
1!
1)
b1101 ?

#360000
0!
0)

#370000
1!
1)
b1110 ?

#380000
0!
0)

#390000
1!
1)
b1111 ?

#400000
0!
0)

#410000
1!
1)
b10000 ?

#420000
0!
0)

#430000
1!
1)
b10001 ?

#440000
0!
0)

#450000
1!
1)
b10010 ?

#460000
0!
0)

#470000
1!
1)
b10011 ?

#480000
0!
0)

#490000
1!
1)
b10100 ?

#500000
0!
0)

#510000
1!
1)
b10101 ?

#520000
0!
0)

#530000
1!
1)
b10110 ?

#540000
0!
0)

#550000
1!
1)
b10111 ?

#560000
0!
0)

#570000
1!
1)
b11000 ?

#580000
0!
0)

#590000
1!
1)
b11001 ?

#600000
0!
0)

#610000
1!
1)
b11010 ?

#620000
0!
0)

#630000
1!
1)
b11011 ?

#640000
0!
0)

#650000
1!
1)
b11100 ?

#660000
0!
0)

#670000
1!
1)
b11101 ?

#680000
0!
0)

#690000
1!
1)
b11110 ?

#700000
0!
0)

#710000
1!
1)
b11111 ?

#720000
0!
0)

#730000
1!
1)
b100000 ?

#740000
0!
0)

#750000
1!
1)
b100001 ?

#760000
0!
0)

#770000
1!
1)
b100010 ?

#780000
0!
0)

#790000
1!
1)
b100011 ?

#800000
0!
0)

#810000
1!
1)
b100100 ?

#820000
0!
0)

#830000
1!
1)
b100101 ?

#840000
0!
0)

#850000
1!
1)
b100110 ?

#860000
0!
0)

#870000
1!
1)
b100111 ?

#880000
0!
0)

#890000
1!
1)
b101000 ?

#900000
0!
0)

#910000
1!
1)
b101001 ?

#920000
0!
0)

#930000
1!
1)
b101010 ?

#940000
0!
0)

#950000
1!
1)
b101011 ?

#960000
0!
0)

#970000
1!
1)
b101100 ?

#980000
0!
0)

#990000
1!
1)
b101101 ?
